{"contents":[
  {
    "id": 109,
    "description": "Want to see what we are all about?  read more...\n",
    "title": "Meetups",
    "isPublic": true,
    "isDraft": false,
    "type": "module",
    "level": 2,
    "parent": null,
    "children": [],
    "path": "D:\\my-projects\\DELFT-OPEN-HARDWARE\\REPOS\\delftoh\\src\\events\\",
    "relativePath": "/events/",
    "authors": ""
  },
  {
    "id": 749,
    "description": "For students, researchers, professors, staff and beyond\n",
    "title": "Getting involved",
    "isPublic": true,
    "isDraft": false,
    "type": "module",
    "level": 2,
    "parent": null,
    "children": [],
    "path": "D:\\my-projects\\DELFT-OPEN-HARDWARE\\REPOS\\delftoh\\src\\get_involved\\",
    "relativePath": "/get_involved/",
    "authors": ""
  },
  {
    "id": 482,
    "description": "Find out what we do, how you can support and how to suggest projects\n",
    "title": "Projects",
    "isPublic": true,
    "isDraft": false,
    "type": "module",
    "level": 2,
    "parent": null,
    "children": [],
    "path": "D:\\my-projects\\DELFT-OPEN-HARDWARE\\REPOS\\delftoh\\src\\projects\\",
    "relativePath": "/projects/",
    "authors": ""
  }
]}